mtnetbri/__init__.py
mtnetbri/__main__.py
mtnetbri-1.0.7.dist-info/LICENSE.txt
mtnetbri-1.0.7.dist-info/METADATA
mtnetbri-1.0.7.dist-info/WHEEL
mtnetbri-1.0.7.dist-info/top_level.txt
mtnetbri-1.0.7.dist-info/RECORD
