Metadata-Version: 2.1
Name: mtnetbri
Version: 1.0.7
Summary: mtnetbri
Home-page: https://github.com/pythonsystem/mtnetbri
Author: Lucas Campagna
License: MIT
License-File: LICENSE.txt
Requires-Dist: pyparsing ==3.1.2
Requires-Dist: rpyc ==5.2.3
Requires-Dist: plumbum ==1.7.0
Requires-Dist: numpy ==1.24.3
